najaeda/instance_visitor.py
najaeda/naja.pyd
najaeda/naja_bne.dll
najaeda/naja_dnl.dll
najaeda/naja_metrics.dll
najaeda/naja_nl.dll
najaeda/naja_opt.dll
najaeda/naja_python.dll
najaeda/netlist.py
najaeda/net_visitor.py
najaeda/pandas_stats.py
najaeda/stats.py
najaeda/_version.py
najaeda/__init__.py
najaeda/docs/.readthedocs.yaml
najaeda/docs/requirements.txt
najaeda/docs/source/api.rst
najaeda/docs/source/common_classes.rst
najaeda/docs/source/conf.py
najaeda/docs/source/equipotential.rst
najaeda/docs/source/examples.rst.in
najaeda/docs/source/index.rst
najaeda/docs/source/instance.rst
najaeda/docs/source/introduction.rst
najaeda/docs/source/net.rst
najaeda/docs/source/netlist_classes.rst
najaeda/docs/source/preprocessor.py
najaeda/docs/source/term.rst
najaeda/docs/source/visitors.rst
najaeda/native/stats.py
najaeda/native/__init__.py
najaeda/primitives/utils.py
najaeda/primitives/xilinx.py
najaeda/primitives/yosys.py
najaeda/primitives/__init__.py
najaeda/remote/serialization.py
najaeda/remote/server.py
najaeda/remote/__init__.py
najaeda-0.3.6.dist-info/DELVEWHEEL
najaeda-0.3.6.dist-info/METADATA
najaeda-0.3.6.dist-info/RECORD
najaeda-0.3.6.dist-info/WHEEL
najaeda-0.3.6.dist-info/licenses/AUTHORS
najaeda-0.3.6.dist-info/licenses/LICENSE
najaeda.libs/msvcp140.dll
najaeda.libs/tbb12.dll
najaeda.libs/tbbmalloc.dll
