Metadata-Version: 2.2
Name: najaeda
Version: 0.3.6
Summary: Naja EDA Python package
Author-Email: Naja Authors <contact@keplertech.io>
License: Apache License 2.0
Classifier: Development Status :: 4 - Beta
Classifier: Intended Audience :: Developers
Classifier: License :: OSI Approved :: Apache Software License
Classifier: Operating System :: MacOS
Classifier: Operating System :: POSIX :: Linux
Classifier: Operating System :: Microsoft :: Windows
Classifier: Programming Language :: Python :: 3.9
Classifier: Programming Language :: Python :: 3.10
Classifier: Programming Language :: Python :: 3.11
Classifier: Programming Language :: Python :: 3.12
Classifier: Programming Language :: Python :: 3.13
Classifier: Programming Language :: Python :: 3.14
Classifier: Topic :: Scientific/Engineering :: Electronic Design Automation (EDA)
Project-URL: Homepage, https://github.com/najaeda/naja
Requires-Python: >=3.8
